flake8_import_single/__init__.py
flake8_import_single/linter.py
flake8_import_single/version.py
flake8_import_single-0.1.5.dist-info/METADATA
flake8_import_single-0.1.5.dist-info/RECORD
flake8_import_single-0.1.5.dist-info/WHEEL
flake8_import_single-0.1.5.dist-info/entry_points.txt
flake8_import_single-0.1.5.dist-info/top_level.txt
